CHANGES.txt
LICENSE.txt
MANIFEST.in
README.txt
setup.py
js/__init__.py
js.raven.egg-info/PKG-INFO
js.raven.egg-info/SOURCES.txt
js.raven.egg-info/dependency_links.txt
js.raven.egg-info/entry_points.txt
js.raven.egg-info/namespace_packages.txt
js.raven.egg-info/not-zip-safe
js.raven.egg-info/requires.txt
js.raven.egg-info/top_level.txt
js/raven/__init__.py
js/raven/test_raven.txt
js/raven/resources/raven.js
js/raven/resources/raven.min.js
js/raven/resources/raven.min.js.map
js/raven/resources/raven.min.map