Metadata-Version: 1.0
Name: js.raven
Version: 3.24.2
Summary: Fanstatic packaging of raven-js
Home-page: UNKNOWN
Author: Fanstatic Developers
Author-email: fanstatic@googlegroups.com
License: BSD
Platform: UNKNOWN
